[{"speaker":"SPEAKER_00","text":" This podcast series, Contextualizing Feminist Voices, is designed to provide background","timestamp_start":0,"timestamp_end":12.38,"source":"102"},{"speaker":"SPEAKER_00","text":" information for people using the Global Feminism Project website. The podcast aims to provide","timestamp_start":12.38,"timestamp_end":17.34,"source":"102"},{"speaker":"SPEAKER_00","text":" users with a well-informed perspective on interesting aspects of the interviews from","timestamp_start":17.34,"timestamp_end":21.2,"source":"102"},{"speaker":"SPEAKER_00","text":" a particular country. For each episode, one of the project staff interviews an expert on that country site. Welcome to this episode of Contextualizing","timestamp_start":21.2,"timestamp_end":30.36,"source":"102"},{"speaker":"SPEAKER_02","text":" Feminist Voices. My name is Abigail Dumas. In this episode, I am talking with my University","timestamp_start":30.36,"timestamp_end":36.7,"source":"102"},{"speaker":"SPEAKER_02","text":" of Michigan colleagues, Professor Alicia Rene and doctoral candidate Ronke Oluwole,","timestamp_start":36.7,"timestamp_end":42.18,"source":"102"},{"speaker":"SPEAKER_02","text":" who will provide perspectives on the interviews from Nigeria.","timestamp_start":42.66,"timestamp_end":46.38,"source":"102"},{"speaker":"SPEAKER_02","text":" Time is short, so we\u0027ll dive right in.","timestamp_start":46.96,"timestamp_end":48.78,"source":"102"},{"speaker":"SPEAKER_02","text":" Alicia, what are one or two important things about feminist activism in Nigeria","timestamp_start":50.42,"timestamp_end":55.52,"source":"102"},{"speaker":"SPEAKER_02","text":" for people to keep in mind that are not covered in the written introductory information on the website?","timestamp_start":55.52,"timestamp_end":60.92,"source":"102"},{"speaker":"SPEAKER_02","text":" Thank you, Abby.","timestamp_start":62.12,"timestamp_end":63.26,"source":"102"},{"speaker":"SPEAKER_03","text":" I\u0027d like to say that while the introduction to the Nigerian","timestamp_start":64.02,"timestamp_end":67.58,"source":"102"},{"speaker":"SPEAKER_03","text":" interviews mentions that there are many ethnic groups and religious practices in the country,","timestamp_start":67.58,"timestamp_end":73.26,"source":"102"},{"speaker":"SPEAKER_03","text":" as well as historical analyses which privileged a Western male viewpoint, listeners to these","timestamp_start":73.26,"timestamp_end":80.26,"source":"102"},{"speaker":"SPEAKER_03","text":" interviews might want to think about how women\u0027s cultural backgrounds associated with particular ethnic groups and religions intersect with distinctive feminist views. For what might","timestamp_start":80.26,"timestamp_end":91.56,"source":"102"},{"speaker":"SPEAKER_03","text":" be seen as correct feminist practice by some Nigerian women does not mean that other Nigerian","timestamp_start":91.56,"timestamp_end":97.2,"source":"102"},{"speaker":"SPEAKER_03","text":" women might not have a different feminist position, reflecting the sociocultural and political context","timestamp_start":97.2,"timestamp_end":103.54,"source":"102"},{"speaker":"SPEAKER_03","text":" in which they live. In other words,","timestamp_start":103.54,"timestamp_end":106.02,"source":"102"},{"speaker":"SPEAKER_03","text":" there is no single feminist perspective or practice in Nigeria, although this sometimes","timestamp_start":106.12,"timestamp_end":111.36,"source":"102"},{"speaker":"SPEAKER_03","text":" may appear to be the case. For example, continuing disputes over the wearing of hijab or headscarves","timestamp_start":111.36,"timestamp_end":118.28,"source":"102"},{"speaker":"SPEAKER_03","text":" by Muslim girls attending schools in southern Nigeria reflect these different perspectives.","timestamp_start":118.28,"timestamp_end":123.3,"source":"102"},{"speaker":"SPEAKER_03","text":" Indeed, there have been several newspaper stories","timestamp_start":124.22,"timestamp_end":126.58,"source":"102"},{"speaker":"SPEAKER_03","text":" about these disputes in recent years","timestamp_start":126.58,"timestamp_end":128.62,"source":"102"},{"speaker":"SPEAKER_03","text":" in Ogun, Oyo, and Kwaro states,","timestamp_start":128.62,"timestamp_end":131.2,"source":"102"},{"speaker":"SPEAKER_03","text":" all in southwestern Nigeria.","timestamp_start":131.6,"timestamp_end":133.1,"source":"102"},{"speaker":"SPEAKER_03","text":" One needs to think about how ethnic identity","timestamp_start":134.42,"timestamp_end":137.34,"source":"102"},{"speaker":"SPEAKER_03","text":" and religious belief, colonial history,","timestamp_start":137.34,"timestamp_end":140.08,"source":"102"},{"speaker":"SPEAKER_03","text":" and attitudes toward the West","timestamp_start":140.46,"timestamp_end":141.88,"source":"102"},{"speaker":"SPEAKER_03","text":" intersect with feminism in Nigeria.","timestamp_start":141.88,"timestamp_end":144.2,"source":"102"},{"speaker":"SPEAKER_03","text":" Several women interviewed present different understandings of the term feminism. Thus, Josephine Efa Chukwuma argues","timestamp_start":146.3,"timestamp_end":153.34,"source":"102"},{"speaker":"SPEAKER_03","text":" that as long as you are questioning the treatment of women and fighting social injustices against","timestamp_start":153.34,"timestamp_end":158.44,"source":"102"},{"speaker":"SPEAKER_03","text":" women and girls, you are a feminist. While Meryl Mandara, who also sees herself as a feminist, notes that she","timestamp_start":158.44,"timestamp_end":167.24,"source":"102"},{"speaker":"SPEAKER_03","text":" looks at feminism within the milieu that I find myself in, which is also about respect for men.","timestamp_start":167.24,"timestamp_end":174.02,"source":"102"},{"speaker":"SPEAKER_03","text":" Their different perspectives reflect how Nigerian feminists with different backgrounds and working","timestamp_start":175.28,"timestamp_end":180.44,"source":"102"},{"speaker":"SPEAKER_03","text":" in different parts of the country need to consider socio-cultural beliefs","timestamp_start":180.44,"timestamp_end":185.46,"source":"102"},{"speaker":"SPEAKER_03","text":" and local practices in order to successfully","timestamp_start":185.46,"timestamp_end":188.48,"source":"102"},{"speaker":"SPEAKER_03","text":" implement their programs.","timestamp_start":188.48,"timestamp_end":190.26,"source":"102"},{"speaker":"SPEAKER_02","text":" Franke, we have learned that some topics","timestamp_start":191.1,"timestamp_end":193.46,"source":"102"},{"speaker":"SPEAKER_02","text":" that would be illuminating about women\u0027s movements","timestamp_start":193.46,"timestamp_end":195.56,"source":"102"},{"speaker":"SPEAKER_02","text":" in a particular setting do not get covered in interviews","timestamp_start":195.56,"timestamp_end":198.52,"source":"102"},{"speaker":"SPEAKER_02","text":" for a variety of reasons.","timestamp_start":198.52,"timestamp_end":200.3,"source":"102"},{"speaker":"SPEAKER_02","text":" Are there any topics that you\u0027d like to point out","timestamp_start":200.3,"timestamp_end":202.3,"source":"102"},{"speaker":"SPEAKER_02","text":" that are missing from the interviews?","timestamp_start":202.3,"timestamp_end":204.1,"source":"102"},{"speaker":"SPEAKER_02","text":" Yes, thank you, Abby.","timestamp_start":205.12,"timestamp_end":206.46,"source":"102"},{"speaker":"SPEAKER_01","text":" Really, there are two topics I would like to just kind of talk about, and this will","timestamp_start":207.22,"timestamp_end":212.42,"source":"102"},{"speaker":"SPEAKER_01","text":" be the issue of submission in Nigeria context and how the success of the child is placed","timestamp_start":212.42,"timestamp_end":220.8,"source":"102"},{"speaker":"SPEAKER_01","text":" in the woman.","timestamp_start":220.8,"timestamp_end":222.42,"source":"102"},{"speaker":"SPEAKER_01","text":" And we don\u0027t think of how these two issues","timestamp_start":222.42,"timestamp_end":225.74,"source":"102"},{"speaker":"SPEAKER_01","text":" actually affect the mental health of the woman","timestamp_start":225.74,"timestamp_end":229.08,"source":"102"},{"speaker":"SPEAKER_01","text":" at the end of the day.","timestamp_start":229.08,"timestamp_end":230.22,"source":"102"},{"speaker":"SPEAKER_01","text":" Let\u0027s think about African feminism","timestamp_start":230.82,"timestamp_end":232.54,"source":"102"},{"speaker":"SPEAKER_01","text":" and how the experiences of women in different backgrounds","timestamp_start":232.54,"timestamp_end":236.46,"source":"102"},{"speaker":"SPEAKER_01","text":" are not often covered in a lot of the things","timestamp_start":236.46,"timestamp_end":239.66,"source":"102"},{"speaker":"SPEAKER_01","text":" that we read and write about.","timestamp_start":239.66,"timestamp_end":241.6,"source":"102"},{"speaker":"SPEAKER_01","text":" First, so submission in the Nigerian context","timestamp_start":241.96,"timestamp_end":244.6,"source":"102"},{"speaker":"SPEAKER_01","text":" means that the woman needs,","timestamp_start":244.6,"timestamp_end":246.56,"source":"102"},{"speaker":"SPEAKER_01","text":" for instance, to submit to the point of submitting her paycheck on livelihood to her husband.","timestamp_start":246.56,"timestamp_end":256.06,"source":"102"},{"speaker":"SPEAKER_01","text":" And the point at which where she thinks she\u0027s done with this and doesn\u0027t want to continue to","timestamp_start":256.42,"timestamp_end":261.6,"source":"102"},{"speaker":"SPEAKER_01","text":" give him all that she earns is where trouble begins.","timestamp_start":261.6,"timestamp_end":265.14,"source":"102"},{"speaker":"SPEAKER_01","text":" And we see how this is still playing out.","timestamp_start":265.7,"timestamp_end":267.9,"source":"102"},{"speaker":"SPEAKER_01","text":" And I do have a personal experience, for instance, the day that my mother, after 10 years,","timestamp_start":267.9,"timestamp_end":274.44,"source":"102"},{"speaker":"SPEAKER_01","text":" decided that she would no longer give her paycheck as a school teacher to my father","timestamp_start":274.54,"timestamp_end":279.44,"source":"102"},{"speaker":"SPEAKER_01","text":" was the day she began to be looked at as a proud woman,","timestamp_start":279.44,"timestamp_end":283.16,"source":"102"},{"speaker":"SPEAKER_01","text":" until she was eventually kicked out of the home","timestamp_start":284.02,"timestamp_end":287.74,"source":"102"},{"speaker":"SPEAKER_01","text":" and this is not often uh written about or discussed in the popular media because it\u0027s not","timestamp_start":287.74,"timestamp_end":295.7,"source":"102"},{"speaker":"SPEAKER_01","text":" like very uh maybe obvious amongst the experiences of women but we also have","timestamp_start":295.7,"timestamp_end":302.64,"source":"102"},{"speaker":"SPEAKER_01","text":" situations where the livelihoods of women,","timestamp_start":302.64,"timestamp_end":305.76,"source":"102"},{"speaker":"SPEAKER_01","text":" whether through their livestock or the monies they make through their businesses,","timestamp_start":305.76,"timestamp_end":309.52,"source":"102"},{"speaker":"SPEAKER_01","text":" have to be given to the man who at the end of the day takes the money, whether to go on a","timestamp_start":309.52,"timestamp_end":315.6,"source":"102"},{"speaker":"SPEAKER_01","text":" drinking spree with his friends, and the woman cannot ask questions about how her money is being spent. So the issue, for instance, about joint accounts","timestamp_start":315.6,"timestamp_end":327.16,"source":"102"},{"speaker":"SPEAKER_01","text":" is not very popular because many women are coming to the realization that it\u0027s not something they","timestamp_start":327.16,"timestamp_end":333.42,"source":"102"},{"speaker":"SPEAKER_01","text":" want to continue to practice because it has not worked for them, not for their children.","timestamp_start":333.42,"timestamp_end":338.82,"source":"102"},{"speaker":"SPEAKER_01","text":" Then the other thing I wanted to talk about is the issue of the success of the child.","timestamp_start":339.84,"timestamp_end":344.24,"source":"102"},{"speaker":"SPEAKER_01","text":" And the other thing I wanted to talk about is the issue of the success of the child.","timestamp_start":344.24,"timestamp_end":345.16,"source":"102"},{"speaker":"SPEAKER_01","text":" There\u0027s actually an adage that a child that succeeds belongs to the father, while the child that fails is the mother\u0027s.","timestamp_start":353.3,"timestamp_end":353.92,"source":"102"},{"speaker":"SPEAKER_01","text":" So you hear them say, go and meet your mother.","timestamp_start":356.42,"timestamp_end":356.76,"source":"102"},{"speaker":"SPEAKER_01","text":" You look like your mother.","timestamp_start":357.8,"timestamp_end":358.08,"source":"102"},{"speaker":"SPEAKER_01","text":" And it\u0027s worse where it\u0027s a female child. So you find so many women in Nigeria remain in these suppressive, abusive, repressive","timestamp_start":360.6,"timestamp_end":369.64,"source":"102"},{"speaker":"SPEAKER_01","text":" relationships just because they want to stay married because of their children.","timestamp_start":369.64,"timestamp_end":375.3,"source":"102"},{"speaker":"SPEAKER_01","text":" And they pour out all their energy and the success of the child so that at the end of the day, they know that if the child does not do well,","timestamp_start":376.04,"timestamp_end":386.22,"source":"102"},{"speaker":"SPEAKER_01","text":" they have not succeeded, whether in business or in marriage. I see how this has affected a lot","timestamp_start":387.04,"timestamp_end":395.54,"source":"102"},{"speaker":"SPEAKER_01","text":" of women who we hear and read about die suddenly and nobody ever diagnoses the causes of their deaths. Yeah.","timestamp_start":395.54,"timestamp_end":405.44,"source":"102"},{"speaker":"SPEAKER_02","text":" Thank you both so much.","timestamp_start":406.26,"timestamp_end":407.76,"source":"102"},{"speaker":"SPEAKER_02","text":" That was illuminating.","timestamp_start":407.84,"timestamp_end":408.72,"source":"102"},{"speaker":"SPEAKER_02","text":" And we really appreciate your perspectives on the interviews.","timestamp_start":408.98,"timestamp_end":411.44,"source":"102"},{"speaker":"SPEAKER_00","text":" Thank you for listening to this episode of Contextualizing Feminist Voices, created by the Global Feminisms Project.","timestamp_start":412.52,"timestamp_end":418.4,"source":"102"},{"speaker":"SPEAKER_00","text":" The entire podcast team hopes it will help you understand and enjoy the materials on the website.","timestamp_start":418.52,"timestamp_end":423.36,"source":"102"},{"speaker":"SPEAKER_00","text":" hopes it will help you understand and enjoy the materials on the website.","timestamp_start":423.36,"timestamp_end":423.88,"source":"102"},{"speaker":"SPEAKER_00","text":" If you liked this episode, check out the other podcasts in this series,","timestamp_start":426.8,"timestamp_end":427.2,"source":"102"}]